poker/__init__.py
poker/cpoker.cpython-37m-darwin.so
poker/poker.py
poker/poker_lite.py
poker/tests.py
poker/utils.py
poker/__pycache__/__init__.cpython-37.pyc
poker/__pycache__/poker.cpython-37.pyc
poker/__pycache__/poker_lite.cpython-37.pyc
poker/__pycache__/tests.cpython-37.pyc
poker/__pycache__/utils.cpython-37.pyc
pokyr-0.1.24.dist-info/LICENSE
pokyr-0.1.24.dist-info/METADATA
pokyr-0.1.24.dist-info/WHEEL
pokyr-0.1.24.dist-info/top_level.txt
pokyr-0.1.24.dist-info/RECORD
