Metadata-Version: 2.1
Name: pokyr
Version: 0.1.24
Summary: Poker hand evaluating modules that provide fast enumerations.
Home-page: https://github.com/cleverpiggy/pokyr
Author: Allen Boyd Cunningham
Author-email: cleverfoundation@gmail.com
License: GPL
Platform: UNKNOWN
Classifier: Programming Language :: Python
Classifier: Programming Language :: C
Classifier: License :: OSI Approved :: GNU General Public License (GPL)
Classifier: Operating System :: POSIX :: Linux
Classifier: Operating System :: MacOS :: MacOS X
Classifier: Intended Audience :: Developers
Classifier: Topic :: Games/Entertainment
